candid/__init__.py
candid/client.py
candid/core/__init__.py
candid/core/api_error.py
candid/core/client_wrapper.py
candid/core/datetime_utils.py
candid/core/file.py
candid/core/force_multipart.py
candid/core/http_client.py
candid/core/http_response.py
candid/core/jsonable_encoder.py
candid/core/oauth_token_provider.py
candid/core/pydantic_utilities.py
candid/core/query_encoder.py
candid/core/remove_none_from_dict.py
candid/core/request_options.py
candid/core/serialization.py
candid/environment.py
candid/py.typed
candid/resources/__init__.py
candid/resources/auth/__init__.py
candid/resources/auth/client.py
candid/resources/auth/raw_client.py
candid/resources/auth/resources/__init__.py
candid/resources/auth/resources/default/__init__.py
candid/resources/auth/resources/default/client.py
candid/resources/auth/resources/default/errors/__init__.py
candid/resources/auth/resources/default/errors/invalid_content_type_error.py
candid/resources/auth/resources/default/errors/too_many_requests_error.py
candid/resources/auth/resources/default/raw_client.py
candid/resources/auth/resources/default/types/__init__.py
candid/resources/auth/resources/default/types/auth_get_token_response.py
candid/resources/auth/resources/default/types/invalid_content_type_error_type.py
candid/resources/auth/resources/default/types/too_many_requests_error_type.py
candid/resources/billing_notes/__init__.py
candid/resources/billing_notes/client.py
candid/resources/billing_notes/raw_client.py
candid/resources/billing_notes/resources/__init__.py
candid/resources/billing_notes/resources/v_2/__init__.py
candid/resources/billing_notes/resources/v_2/client.py
candid/resources/billing_notes/resources/v_2/raw_client.py
candid/resources/billing_notes/resources/v_2/types/__init__.py
candid/resources/billing_notes/resources/v_2/types/billing_note.py
candid/resources/billing_notes/resources/v_2/types/billing_note_base.py
candid/resources/billing_notes/resources/v_2/types/billing_note_base_optional.py
candidhealth-1.17.4.dist-info/METADATA
candidhealth-1.17.4.dist-info/WHEEL
candidhealth-1.17.4.dist-info/RECORD
